mad_import/__init__.py
mad_import/mad_import.py
mad_import-0.0.dev0.dist-info/METADATA
mad_import-0.0.dev0.dist-info/WHEEL
mad_import-0.0.dev0.dist-info/entry_points.txt
mad_import-0.0.dev0.dist-info/top_level.txt
mad_import-0.0.dev0.dist-info/zip-safe
mad_import-0.0.dev0.dist-info/RECORD
